streamlit_picture_in_picture_video/__init__.py
streamlit_picture_in_picture_video/example.py
streamlit_picture_in_picture_video-0.1.1.dist-info/licenses/LICENSE
streamlit_picture_in_picture_video-0.1.1.dist-info/METADATA
streamlit_picture_in_picture_video-0.1.1.dist-info/WHEEL
streamlit_picture_in_picture_video-0.1.1.dist-info/top_level.txt
streamlit_picture_in_picture_video-0.1.1.dist-info/RECORD
