Metadata-Version: 2.4
Name: streamlit-picture-in-picture-video
Version: 0.1.1
Summary: Streamlit component that allows you to render a video in picture-in-picture mode
Home-page: 
Author: Matthias Bloch
Author-email: 7060663+matbloch@users.noreply.github.com
Requires-Python: >=3.7
License-File: LICENSE
Requires-Dist: streamlit>=1.2
Provides-Extra: devel
Requires-Dist: wheel; extra == "devel"
Requires-Dist: pytest==7.4.0; extra == "devel"
Requires-Dist: playwright==1.48.0; extra == "devel"
Requires-Dist: requests==2.31.0; extra == "devel"
Requires-Dist: pytest-playwright-snapshot==1.0; extra == "devel"
Requires-Dist: pytest-rerunfailures==12.0; extra == "devel"
Dynamic: author
Dynamic: author-email
Dynamic: description
Dynamic: description-content-type
Dynamic: license-file
Dynamic: provides-extra
Dynamic: requires-dist
Dynamic: requires-python
Dynamic: summary
